[
    {
        "id": "72dd23b68",
        "results": [
            {
                "name": "Max Gunther",
                "countryCode": "DE",
                "team": "DS Penske",
                "time": "1:06.050",
                "laps": 18
            },
            {
                "name": "Antonio Felix Da Costa",
                "countryCode": "PT",
                "team": "TAG Heuer Porsche",
                "time": "+0.292",
                "laps": 23
            },
            {
                "name": "Edoardo Mortara",
                "countryCode": "IT",
                "team": "Mahindra Racing",
                "time": "+0.334",
                "laps": 23
            },
            {
                "name": "Oliver Rowland",
                "countryCode": "GB",
                "team": "Nissan E.dams",
                "time": "+0.348",
                "laps": 16
            },
            {
                "name": "Nico Muller",
                "countryCode": "CH",
                "team": "Andretti Formula E",
                "time": "+0.394",
                "laps": 24
            },
            {
                "name": "Mitch Evans",
                "countryCode": "NZ",
                "team": "Jaguar Racing",
                "time": "+0.410",
                "laps": 22
            },
            {
                "name": "Nick Cassidy",
                "countryCode": "NZ",
                "team": "Jaguar Racing",
                "time": "+0.489",
                "laps": 23
            },
            {
                "name": "Dan Ticktum",
                "countryCode": "GB",
                "team": "Cupra Kiro",
                "time": "+0.558",
                "laps": 24
            },
            {
                "name": "Jean-Eric Vergne",
                "countryCode": "FR",
                "team": "DS Penske",
                "time": "+0.607",
                "laps": 21
            },
            {
                "name": "David Beckmann",
                "countryCode": "DE",
                "team": "Cupra Kiro",
                "time": "+0.670",
                "laps": 20
            },
            {
                "name": "Norman Nato",
                "countryCode": "FR",
                "team": "Nissan E.dams",
                "time": "+0.730",
                "laps": 19
            },
            {
                "name": "Nyck de Vries",
                "countryCode": "NL",
                "team": "Mahindra Racing",
                "time": "+0.854",
                "laps": 23
            },
            {
                "name": "Jake Dennis",
                "countryCode": "GB",
                "team": "Andretti Formula E",
                "time": "+0.930",
                "laps": 19
            },
            {
                "name": "Taylor Barnard",
                "countryCode": "GB",
                "team": "McLaren Racing",
                "time": "+0.974",
                "laps": 21
            },
            {
                "name": "Sebastien Buemi",
                "countryCode": "CH",
                "team": "Envision Racing",
                "time": "+1.053",
                "laps": 23
            },
            {
                "name": "Jake Hughes",
                "countryCode": "GB",
                "team": "Maserati Racing",
                "time": "+1.060",
                "laps": 17
            },
            {
                "name": "Stoffel Vandoorne",
                "countryCode": "BE",
                "team": "Maserati Racing",
                "time": "+1.111",
                "laps": 19
            },
            {
                "name": "Pascal Wehrlein",
                "countryCode": "DE",
                "team": "TAG Heuer Porsche",
                "time": "+1.159",
                "laps": 19
            },
            {
                "name": "Zane Maloney",
                "countryCode": "BB",
                "team": "Lola Yamaha ABT",
                "time": "+1.250",
                "laps": 21
            },
            {
                "name": "Sam Bird",
                "countryCode": "GB",
                "team": "McLaren Racing",
                "time": "+1.355",
                "laps": 18
            },
            {
                "name": "Lucas Di Grassi",
                "countryCode": "BR",
                "team": "Lola Yamaha ABT",
                "time": "+1.448",
                "laps": 21
            },
            {
                "name": "Robin Frijns",
                "countryCode": "NL",
                "team": "Envision Racing",
                "time": "+3.851",
                "laps": 6
            }
        ]
    }
]