[
    {
        "id": "6cb5da351",
        "results": [
            {
                "name": "HYP - Philip Hanson",
                "countryCode": null,
                "team": null,
                "time": "3:26.523",
                "laps": 10
            },
            {
                "name": "HYP - Antonio Fuoco",
                "countryCode": null,
                "team": null,
                "time": "+0.933",
                "laps": 12
            },
            {
                "name": "HYP - Jack Aitken",
                "countryCode": null,
                "team": null,
                "time": "+1.257",
                "laps": 12
            },
            {
                "name": "HYP - Jenson Button",
                "countryCode": null,
                "team": null,
                "time": "+1.370",
                "laps": 12
            },
            {
                "name": "HYP - Kévin Estre",
                "countryCode": null,
                "team": null,
                "time": "+1.396",
                "laps": 15
            },
            {
                "name": "HYP - Norman Nato",
                "countryCode": null,
                "team": null,
                "time": "+1.468",
                "laps": 10
            },
            {
                "name": "HYP - Alessandro Pier Guidi",
                "countryCode": null,
                "team": null,
                "time": "+1.626",
                "laps": 11
            },
            {
                "name": "HYP - Mathieu Jaminet",
                "countryCode": null,
                "team": null,
                "time": "+1.808",
                "laps": 10
            },
            {
                "name": "HYP - Sébastien Buemi",
                "countryCode": null,
                "team": null,
                "time": "+1.809",
                "laps": 14
            },
            {
                "name": "HYP - Paul-Loup Chatin",
                "countryCode": null,
                "team": null,
                "time": "+1.823",
                "laps": 14
            },
            {
                "name": "HYP - Pascal Wehrlein",
                "countryCode": null,
                "team": null,
                "time": "+2.137",
                "laps": 11
            },
            {
                "name": "HYP - Nyck de Vries",
                "countryCode": null,
                "team": null,
                "time": "+2.156",
                "laps": 15
            },
            {
                "name": "HYP - René Rast",
                "countryCode": null,
                "team": null,
                "time": "+2.574",
                "laps": 10
            },
            {
                "name": "HYP - Mick Schumacher",
                "countryCode": null,
                "team": null,
                "time": "+2.708",
                "laps": 13
            },
            {
                "name": "HYP - Filipe Albuquerque",
                "countryCode": null,
                "team": null,
                "time": "+2.818",
                "laps": 9
            },
            {
                "name": "HYP - Loïc Duval",
                "countryCode": null,
                "team": null,
                "time": "+2.878",
                "laps": 15
            },
            {
                "name": "HYP - Nicolás Varrone",
                "countryCode": null,
                "team": null,
                "time": "+3.575",
                "laps": 12
            },
            {
                "name": "HYP - Paul Di Resta",
                "countryCode": null,
                "team": null,
                "time": "+3.575",
                "laps": 15
            },
            {
                "name": "HYP - Ross Gunn",
                "countryCode": null,
                "team": null,
                "time": "+4.338",
                "laps": 14
            },
            {
                "name": "HYP - Alex Riberas",
                "countryCode": null,
                "team": null,
                "time": "+7.873",
                "laps": 5
            },
            {
                "name": "GT3 - Franck Perera",
                "countryCode": null,
                "team": null,
                "time": "+11.779",
                "laps": 12
            },
            {
                "name": "GT3 - Mathias Beche",
                "countryCode": null,
                "team": null,
                "time": "+12.407",
                "laps": 12
            },
            {
                "name": "GT3 - Matthieu Vaxiviere",
                "countryCode": null,
                "team": null,
                "time": "+12.452",
                "laps": 13
            },
            {
                "name": "GT3 - Bent Viscaal",
                "countryCode": null,
                "team": null,
                "time": "+12.569",
                "laps": 13
            },
            {
                "name": "GT3 - Nicholas BOULLE",
                "countryCode": null,
                "team": null,
                "time": "+12.609",
                "laps": 13
            },
            {
                "name": "GT3 - Cem Bölükbaşi",
                "countryCode": null,
                "team": null,
                "time": "+13.302",
                "laps": 13
            },
            {
                "name": "GT3 - Reshad De Gérus",
                "countryCode": null,
                "team": null,
                "time": "+13.745",
                "laps": 14
            },
            {
                "name": "GT3 - David Heinemeier Hansson",
                "countryCode": null,
                "team": null,
                "time": "+13.842",
                "laps": 9
            },
            {
                "name": "GT3 - Daniel Schneider",
                "countryCode": null,
                "team": null,
                "time": "+13.880",
                "laps": 6
            },
            {
                "name": "GT3 - Jamie Chadwick",
                "countryCode": null,
                "team": null,
                "time": "+13.946",
                "laps": 14
            },
            {
                "name": "GT3 - Aliaksandr Malykhin",
                "countryCode": null,
                "team": null,
                "time": "+13.970",
                "laps": 13
            },
            {
                "name": "GT3 - Tom Dillmann",
                "countryCode": null,
                "team": null,
                "time": "+15.680",
                "laps": 8
            },
            {
                "name": "GT3 - Sebastian Alvarez",
                "countryCode": null,
                "team": null,
                "time": "+15.935",
                "laps": 13
            },
            {
                "name": "GT3 - PJ Hyett",
                "countryCode": null,
                "team": null,
                "time": "+17.586",
                "laps": 12
            },
            {
                "name": "GT3 - Michael Jensen",
                "countryCode": null,
                "team": null,
                "time": "+23.887",
                "laps": 10
            },
            {
                "name": "GT3 - Jose Maria Lopez",
                "countryCode": null,
                "team": null,
                "time": "+28.534",
                "laps": 11
            },
            {
                "name": "GT3 - Valentin Hasse Clot",
                "countryCode": null,
                "team": null,
                "time": "+29.702",
                "laps": 13
            },
            {
                "name": "GT3 - Francesco Castellacci",
                "countryCode": null,
                "team": null,
                "time": "+29.910",
                "laps": 8
            },
            {
                "name": "GT3 - Casper Stevenson",
                "countryCode": null,
                "team": null,
                "time": "+29.990",
                "laps": 13
            },
            {
                "name": "GT3 - Bernardo Sousa",
                "countryCode": null,
                "team": null,
                "time": "+30.761",
                "laps": 12
            },
            {
                "name": "GT3 - Riccardo Agostini",
                "countryCode": null,
                "team": null,
                "time": "+30.803",
                "laps": 12
            },
            {
                "name": "GT3 - Simon Mann",
                "countryCode": null,
                "team": null,
                "time": "+31.356",
                "laps": 10
            },
            {
                "name": "GT3 - jonathan hui",
                "countryCode": null,
                "team": null,
                "time": "+31.434",
                "laps": 12
            },
            {
                "name": "GT3 - Arnold Robin",
                "countryCode": null,
                "team": null,
                "time": "+31.528",
                "laps": 10
            },
            {
                "name": "GT3 - Dennis Olsen",
                "countryCode": null,
                "team": null,
                "time": "+31.604",
                "laps": 12
            },
            {
                "name": "GT3 - Rahel Frey",
                "countryCode": null,
                "team": null,
                "time": "+32.093",
                "laps": 13
            },
            {
                "name": "GT3 - Maxime Martin",
                "countryCode": null,
                "team": null,
                "time": "+32.628",
                "laps": 11
            },
            {
                "name": "GT3 - Valentino Rossi",
                "countryCode": null,
                "team": null,
                "time": "+33.173",
                "laps": 13
            },
            {
                "name": "GT3 - Richard Lietz",
                "countryCode": null,
                "team": null,
                "time": "+33.357",
                "laps": 13
            },
            {
                "name": "GT3 - Timur Boguslavskiy",
                "countryCode": null,
                "team": null,
                "time": "+33.593",
                "laps": 13
            },
            {
                "name": "GT3 - Mattia Drudi",
                "countryCode": null,
                "team": null,
                "time": "+33.917",
                "laps": 4
            },
            {
                "name": "GT3 - Orey Fidani",
                "countryCode": null,
                "team": null,
                "time": "+34.002",
                "laps": 13
            },
            {
                "name": "GT3 - Marino Sato",
                "countryCode": null,
                "team": null,
                "time": "+34.217",
                "laps": 10
            },
            {
                "name": "GT3 - Lorcan Hanafin",
                "countryCode": null,
                "team": null,
                "time": "+34.316",
                "laps": 13
            },
            {
                "name": "GT3 - Daniel Juncadella",
                "countryCode": null,
                "team": null,
                "time": "+34.630",
                "laps": 13
            },
            {
                "name": "GT3 - Antares Au",
                "countryCode": null,
                "team": null,
                "time": "+39.419",
                "laps": 11
            },
            {
                "name": "GT3 - Lorenzo Fluxa",
                "countryCode": null,
                "team": null,
                "time": "+1:08.069",
                "laps": 6
            },
            {
                "name": "GT3 - George Kurtz",
                "countryCode": null,
                "team": null,
                "time": "+1:50.488",
                "laps": 5
            },
            {
                "name": "HYP - Kevin MAGNUSSEN",
                "countryCode": null,
                "team": null,
                "time": "+0.000",
                "laps": 2
            },
            {
                "name": "GT3 - James Cottingham",
                "countryCode": null,
                "team": null,
                "laps": 0
            },
            {
                "name": "GT3 - Brenton Grove",
                "countryCode": null,
                "team": null,
                "time": "+0.000",
                "laps": 1
            },
            {
                "name": "GT3 - Tom Van Rompuy",
                "countryCode": null,
                "team": null,
                "laps": 0
            }
        ]
    },
    {
        "id": "2175f8c5c",
        "results": [
            {
                "name": "GT3 - Mathias Beche",
                "countryCode": null,
                "team": null,
                "time": "3:35.062",
                "laps": 4
            },
            {
                "name": "GT3 - Tom Dillmann",
                "countryCode": null,
                "team": null,
                "time": "+0.271",
                "laps": 4
            },
            {
                "name": "GT3 - Louis Delétraz",
                "countryCode": null,
                "team": null,
                "time": "+0.359",
                "laps": 5
            },
            {
                "name": "GT3 - Benjamin Hanley",
                "countryCode": null,
                "team": null,
                "time": "+0.397",
                "laps": 4
            },
            {
                "name": "GT3 - Pietro Fittipaldi",
                "countryCode": null,
                "team": null,
                "time": "+0.553",
                "laps": 4
            },
            {
                "name": "GT3 - Tom Blomqvist",
                "countryCode": null,
                "team": null,
                "time": "+1.122",
                "laps": 4
            },
            {
                "name": "GT3 - Matthieu Vaxiviere",
                "countryCode": null,
                "team": null,
                "time": "+1.931",
                "laps": 4
            },
            {
                "name": "GT3 - Ryan Cullen",
                "countryCode": null,
                "team": null,
                "time": "+3.860",
                "laps": 4
            },
            {
                "name": "GT3 - Mattia Drudi",
                "countryCode": null,
                "team": null,
                "time": "+17.727",
                "laps": 4
            },
            {
                "name": "GT3 - Alessio Rovera",
                "countryCode": null,
                "team": null,
                "time": "+18.023",
                "laps": 4
            },
            {
                "name": "GT3 - Valentino Rossi",
                "countryCode": null,
                "team": null,
                "time": "+19.904",
                "laps": 4
            },
            {
                "name": "GT3 - Maxime Martin",
                "countryCode": null,
                "team": null,
                "time": "+19.936",
                "laps": 4
            },
            {
                "name": "GT3 - Richard Lietz",
                "countryCode": null,
                "team": null,
                "time": "+20.078",
                "laps": 4
            },
            {
                "name": "GT3 - Rui Andrade",
                "countryCode": null,
                "team": null,
                "time": "+20.678",
                "laps": 4
            },
            {
                "name": "GT3 - Marino Sato",
                "countryCode": null,
                "team": null,
                "time": "+20.903",
                "laps": 4
            },
            {
                "name": "GT3 - Jack Hawksworth",
                "countryCode": null,
                "team": null,
                "time": "+28.598",
                "laps": 4
            }
        ]
    },
    {
        "id": "477bdb55b",
        "results": [
            {
                "name": "GT3 - Mathias Beche",
                "countryCode": null,
                "team": null,
                "time": "3:35.062",
                "laps": 4
            },
            {
                "name": "GT3 - Tom Dillmann",
                "countryCode": null,
                "team": null,
                "time": "+0.271",
                "laps": 4
            },
            {
                "name": "GT3 - Louis Delétraz",
                "countryCode": null,
                "team": null,
                "time": "+0.359",
                "laps": 5
            },
            {
                "name": "GT3 - Benjamin Hanley",
                "countryCode": null,
                "team": null,
                "time": "+0.397",
                "laps": 4
            },
            {
                "name": "GT3 - Pietro Fittipaldi",
                "countryCode": null,
                "team": null,
                "time": "+0.553",
                "laps": 4
            },
            {
                "name": "GT3 - Tom Blomqvist",
                "countryCode": null,
                "team": null,
                "time": "+1.122",
                "laps": 4
            },
            {
                "name": "GT3 - Matthieu Vaxiviere",
                "countryCode": null,
                "team": null,
                "time": "+1.931",
                "laps": 4
            },
            {
                "name": "GT3 - Ryan Cullen",
                "countryCode": null,
                "team": null,
                "time": "+3.860",
                "laps": 4
            },
            {
                "name": "GT3 - Mattia Drudi",
                "countryCode": null,
                "team": null,
                "time": "+17.727",
                "laps": 4
            },
            {
                "name": "GT3 - Alessio Rovera",
                "countryCode": null,
                "team": null,
                "time": "+18.023",
                "laps": 4
            },
            {
                "name": "GT3 - Valentino Rossi",
                "countryCode": null,
                "team": null,
                "time": "+19.904",
                "laps": 4
            },
            {
                "name": "GT3 - Maxime Martin",
                "countryCode": null,
                "team": null,
                "time": "+19.936",
                "laps": 4
            },
            {
                "name": "GT3 - Richard Lietz",
                "countryCode": null,
                "team": null,
                "time": "+20.078",
                "laps": 4
            },
            {
                "name": "GT3 - Rui Andrade",
                "countryCode": null,
                "team": null,
                "time": "+20.678",
                "laps": 4
            },
            {
                "name": "GT3 - Marino Sato",
                "countryCode": null,
                "team": null,
                "time": "+20.903",
                "laps": 4
            },
            {
                "name": "GT3 - Jack Hawksworth",
                "countryCode": null,
                "team": null,
                "time": "+28.598",
                "laps": 4
            }
        ]
    },
    {
        "id": "4ab50afd6",
        "results": [
            {
                "name": "GT3 - Mathias Beche",
                "countryCode": null,
                "team": null,
                "time": "3:35.062",
                "laps": 4
            },
            {
                "name": "GT3 - Tom Dillmann",
                "countryCode": null,
                "team": null,
                "time": "+0.271",
                "laps": 4
            },
            {
                "name": "GT3 - Louis Delétraz",
                "countryCode": null,
                "team": null,
                "time": "+0.359",
                "laps": 5
            },
            {
                "name": "GT3 - Benjamin Hanley",
                "countryCode": null,
                "team": null,
                "time": "+0.397",
                "laps": 4
            },
            {
                "name": "GT3 - Pietro Fittipaldi",
                "countryCode": null,
                "team": null,
                "time": "+0.553",
                "laps": 4
            },
            {
                "name": "GT3 - Tom Blomqvist",
                "countryCode": null,
                "team": null,
                "time": "+1.122",
                "laps": 4
            },
            {
                "name": "GT3 - Matthieu Vaxiviere",
                "countryCode": null,
                "team": null,
                "time": "+1.931",
                "laps": 4
            },
            {
                "name": "GT3 - Ryan Cullen",
                "countryCode": null,
                "team": null,
                "time": "+3.860",
                "laps": 4
            },
            {
                "name": "GT3 - Mattia Drudi",
                "countryCode": null,
                "team": null,
                "time": "+17.727",
                "laps": 4
            },
            {
                "name": "GT3 - Alessio Rovera",
                "countryCode": null,
                "team": null,
                "time": "+18.023",
                "laps": 4
            },
            {
                "name": "GT3 - Valentino Rossi",
                "countryCode": null,
                "team": null,
                "time": "+19.904",
                "laps": 4
            },
            {
                "name": "GT3 - Maxime Martin",
                "countryCode": null,
                "team": null,
                "time": "+19.936",
                "laps": 4
            },
            {
                "name": "GT3 - Richard Lietz",
                "countryCode": null,
                "team": null,
                "time": "+20.078",
                "laps": 4
            },
            {
                "name": "GT3 - Rui Andrade",
                "countryCode": null,
                "team": null,
                "time": "+20.678",
                "laps": 4
            },
            {
                "name": "GT3 - Marino Sato",
                "countryCode": null,
                "team": null,
                "time": "+20.903",
                "laps": 4
            },
            {
                "name": "GT3 - Jack Hawksworth",
                "countryCode": null,
                "team": null,
                "time": "+28.598",
                "laps": 4
            }
        ]
    },
    {
        "id": "ad9d4d2bc",
        "results": [
            {
                "name": "HYP - Julien Andlauer",
                "countryCode": null,
                "team": null,
                "time": "3:24.717",
                "laps": 33
            },
            {
                "name": "HYP - Earl Bamber",
                "countryCode": null,
                "team": null,
                "time": "+0.816",
                "laps": 41
            },
            {
                "name": "HYP - Will Stevens",
                "countryCode": null,
                "team": null,
                "time": "+0.892",
                "laps": 40
            },
            {
                "name": "HYP - James Calado",
                "countryCode": null,
                "team": null,
                "time": "+0.988",
                "laps": 44
            },
            {
                "name": "HYP - Robert Kubica",
                "countryCode": null,
                "team": null,
                "time": "+1.605",
                "laps": 29
            },
            {
                "name": "HYP - Robin Frijns",
                "countryCode": null,
                "team": null,
                "time": "+1.650",
                "laps": 32
            },
            {
                "name": "HYP - Felipe Nasr",
                "countryCode": null,
                "team": null,
                "time": "+2.138",
                "laps": 34
            },
            {
                "name": "HYP - Felipe Drugovich",
                "countryCode": null,
                "team": null,
                "time": "+2.197",
                "laps": 39
            },
            {
                "name": "HYP - Antonio Fuoco",
                "countryCode": null,
                "team": null,
                "time": "+2.231",
                "laps": 34
            },
            {
                "name": "HYP - Raffaele Marciello",
                "countryCode": null,
                "team": null,
                "time": "+2.363",
                "laps": 37
            },
            {
                "name": "HYP - Kamui Kobayashi",
                "countryCode": null,
                "team": null,
                "time": "+2.639",
                "laps": 42
            },
            {
                "name": "HYP - Kévin Estre",
                "countryCode": null,
                "team": null,
                "time": "+2.683",
                "laps": 41
            },
            {
                "name": "HYP - Marco Sørensen",
                "countryCode": null,
                "team": null,
                "time": "+2.790",
                "laps": 39
            },
            {
                "name": "HYP - Brendon Hartley",
                "countryCode": null,
                "team": null,
                "time": "+3.024",
                "laps": 45
            },
            {
                "name": "HYP - Mick Schumacher",
                "countryCode": null,
                "team": null,
                "time": "+3.985",
                "laps": 42
            },
            {
                "name": "HYP - Harry Tincknell",
                "countryCode": null,
                "team": null,
                "time": "+4.552",
                "laps": 39
            },
            {
                "name": "HYP - Stoffel Vandoorne",
                "countryCode": null,
                "team": null,
                "time": "+4.575",
                "laps": 41
            },
            {
                "name": "HYP - Ricky Taylor",
                "countryCode": null,
                "team": null,
                "time": "+4.598",
                "laps": 9
            },
            {
                "name": "HYP - Nicolas Pino",
                "countryCode": null,
                "team": null,
                "time": "+4.684",
                "laps": 29
            },
            {
                "name": "HYP - Paul-Loup Chatin",
                "countryCode": null,
                "team": null,
                "time": "+5.318",
                "laps": 36
            },
            {
                "name": "HYP - Mikkel Jensen",
                "countryCode": null,
                "team": null,
                "time": "+5.933",
                "laps": 30
            },
            {
                "name": "GT3 - Rodrigo Sales",
                "countryCode": null,
                "team": null,
                "time": "+12.110",
                "laps": 40
            },
            {
                "name": "GT3 - Benjamin Hanley",
                "countryCode": null,
                "team": null,
                "time": "+12.719",
                "laps": 35
            },
            {
                "name": "GT3 - Nick Yelloly",
                "countryCode": null,
                "team": null,
                "time": "+12.846",
                "laps": 32
            },
            {
                "name": "GT3 - Renger Van Der Zande",
                "countryCode": null,
                "team": null,
                "time": "+12.946",
                "laps": 36
            },
            {
                "name": "GT3 - Louis Delétraz",
                "countryCode": null,
                "team": null,
                "time": "+13.080",
                "laps": 40
            },
            {
                "name": "GT3 - Job Van Uitert",
                "countryCode": null,
                "team": null,
                "time": "+14.027",
                "laps": 27
            },
            {
                "name": "GT3 - George Kurtz",
                "countryCode": null,
                "team": null,
                "time": "+14.028",
                "laps": 32
            },
            {
                "name": "GT3 - Oliver Gray",
                "countryCode": null,
                "team": null,
                "time": "+14.103",
                "laps": 39
            },
            {
                "name": "GT3 - Giorgio Roda",
                "countryCode": null,
                "team": null,
                "time": "+14.438",
                "laps": 35
            },
            {
                "name": "GT3 - Antonio Felix da Costa",
                "countryCode": null,
                "team": null,
                "time": "+14.586",
                "laps": 32
            },
            {
                "name": "GT3 - Patrick Pilet",
                "countryCode": null,
                "team": null,
                "time": "+14.843",
                "laps": 38
            },
            {
                "name": "GT3 - Reshad De Gérus",
                "countryCode": null,
                "team": null,
                "time": "+14.902",
                "laps": 33
            },
            {
                "name": "GT3 - Matthias Kaiser",
                "countryCode": null,
                "team": null,
                "time": "+15.455",
                "laps": 41
            },
            {
                "name": "GT3 - Aliaksandr Malykhin",
                "countryCode": null,
                "team": null,
                "time": "+15.579",
                "laps": 38
            },
            {
                "name": "GT3 - Naveen Rao",
                "countryCode": null,
                "team": null,
                "time": "+15.885",
                "laps": 33
            },
            {
                "name": "GT3 - Jamie Chadwick",
                "countryCode": null,
                "team": null,
                "time": "+16.324",
                "laps": 32
            },
            {
                "name": "GT3 - Jean-Baptiste Simmenauer",
                "countryCode": null,
                "team": null,
                "time": "+17.027",
                "laps": 39
            },
            {
                "name": "GT3 - Zacharie Robichon",
                "countryCode": null,
                "team": null,
                "time": "+31.180",
                "laps": 32
            },
            {
                "name": "GT3 - Richard Lietz",
                "countryCode": null,
                "team": null,
                "time": "+31.217",
                "laps": 38
            },
            {
                "name": "GT3 - Finn Gehrsitz",
                "countryCode": null,
                "team": null,
                "time": "+31.307",
                "laps": 27
            },
            {
                "name": "GT3 - Valentin Hasse Clot",
                "countryCode": null,
                "team": null,
                "time": "+31.891",
                "laps": 36
            },
            {
                "name": "GT3 - Kelvin Van der Linde",
                "countryCode": null,
                "team": null,
                "time": "+32.161",
                "laps": 38
            },
            {
                "name": "GT3 - James Cottingham",
                "countryCode": null,
                "team": null,
                "time": "+32.215",
                "laps": 25
            },
            {
                "name": "GT3 - Thomas Flohr",
                "countryCode": null,
                "team": null,
                "time": "+32.229",
                "laps": 33
            },
            {
                "name": "GT3 - Antares Au",
                "countryCode": null,
                "team": null,
                "time": "+32.278",
                "laps": 36
            },
            {
                "name": "GT3 - Sean GELAEL",
                "countryCode": null,
                "team": null,
                "time": "+32.323",
                "laps": 32
            },
            {
                "name": "GT3 - jonathan hui",
                "countryCode": null,
                "team": null,
                "time": "+32.383",
                "laps": 37
            },
            {
                "name": "GT3 - Jose Maria Lopez",
                "countryCode": null,
                "team": null,
                "time": "+32.412",
                "laps": 31
            },
            {
                "name": "GT3 - Daniel Serra",
                "countryCode": null,
                "team": null,
                "time": "+32.655",
                "laps": 37
            },
            {
                "name": "GT3 - Custodio Toledo",
                "countryCode": null,
                "team": null,
                "time": "+32.665",
                "laps": 35
            },
            {
                "name": "GT3 - Simon Mann",
                "countryCode": null,
                "team": null,
                "time": "+32.694",
                "laps": 35
            },
            {
                "name": "GT3 - Charlie Eastwood",
                "countryCode": null,
                "team": null,
                "time": "+32.778",
                "laps": 38
            },
            {
                "name": "GT3 - Yasser Shahin",
                "countryCode": null,
                "team": null,
                "time": "+32.921",
                "laps": 38
            },
            {
                "name": "GT3 - Daniel Juncadella",
                "countryCode": null,
                "team": null,
                "time": "+33.024",
                "laps": 36
            },
            {
                "name": "GT3 - Ben Tuck",
                "countryCode": null,
                "team": null,
                "time": "+33.320",
                "laps": 34
            },
            {
                "name": "GT3 - Sarah Bovy",
                "countryCode": null,
                "team": null,
                "time": "+33.654",
                "laps": 39
            },
            {
                "name": "GT3 - Maxime Martin",
                "countryCode": null,
                "team": null,
                "time": "+33.713",
                "laps": 35
            },
            {
                "name": "GT3 - Lorcan Hanafin",
                "countryCode": null,
                "team": null,
                "time": "+34.197",
                "laps": 36
            },
            {
                "name": "GT3 - Brenton Grove",
                "countryCode": null,
                "team": null,
                "time": "+34.814",
                "laps": 30
            },
            {
                "name": "GT3 - Stefano Gattuso",
                "countryCode": null,
                "team": null,
                "time": "+35.477",
                "laps": 17
            },
            {
                "name": "GT3 - Lars Kern",
                "countryCode": null,
                "team": null,
                "time": "+35.668",
                "laps": 25
            }
        ]
    },
    {
        "id": "9f4e3847f",
        "results": [
            {
                "name": "HYP - Julien Andlauer",
                "countryCode": null,
                "team": null,
                "time": "3:24.717",
                "laps": 33
            },
            {
                "name": "HYP - Earl Bamber",
                "countryCode": null,
                "team": null,
                "time": "+0.816",
                "laps": 41
            },
            {
                "name": "HYP - Will Stevens",
                "countryCode": null,
                "team": null,
                "time": "+0.892",
                "laps": 40
            },
            {
                "name": "HYP - James Calado",
                "countryCode": null,
                "team": null,
                "time": "+0.988",
                "laps": 44
            },
            {
                "name": "HYP - Robert Kubica",
                "countryCode": null,
                "team": null,
                "time": "+1.605",
                "laps": 29
            },
            {
                "name": "HYP - Robin Frijns",
                "countryCode": null,
                "team": null,
                "time": "+1.650",
                "laps": 32
            },
            {
                "name": "HYP - Felipe Nasr",
                "countryCode": null,
                "team": null,
                "time": "+2.138",
                "laps": 34
            },
            {
                "name": "HYP - Felipe Drugovich",
                "countryCode": null,
                "team": null,
                "time": "+2.197",
                "laps": 39
            },
            {
                "name": "HYP - Antonio Fuoco",
                "countryCode": null,
                "team": null,
                "time": "+2.231",
                "laps": 34
            },
            {
                "name": "HYP - Raffaele Marciello",
                "countryCode": null,
                "team": null,
                "time": "+2.363",
                "laps": 37
            },
            {
                "name": "HYP - Kamui Kobayashi",
                "countryCode": null,
                "team": null,
                "time": "+2.639",
                "laps": 42
            },
            {
                "name": "HYP - Kévin Estre",
                "countryCode": null,
                "team": null,
                "time": "+2.683",
                "laps": 41
            },
            {
                "name": "HYP - Marco Sørensen",
                "countryCode": null,
                "team": null,
                "time": "+2.790",
                "laps": 39
            },
            {
                "name": "HYP - Brendon Hartley",
                "countryCode": null,
                "team": null,
                "time": "+3.024",
                "laps": 45
            },
            {
                "name": "HYP - Mick Schumacher",
                "countryCode": null,
                "team": null,
                "time": "+3.985",
                "laps": 42
            },
            {
                "name": "HYP - Harry Tincknell",
                "countryCode": null,
                "team": null,
                "time": "+4.552",
                "laps": 39
            },
            {
                "name": "HYP - Stoffel Vandoorne",
                "countryCode": null,
                "team": null,
                "time": "+4.575",
                "laps": 41
            },
            {
                "name": "HYP - Ricky Taylor",
                "countryCode": null,
                "team": null,
                "time": "+4.598",
                "laps": 9
            },
            {
                "name": "HYP - Nicolas Pino",
                "countryCode": null,
                "team": null,
                "time": "+4.684",
                "laps": 29
            },
            {
                "name": "HYP - Paul-Loup Chatin",
                "countryCode": null,
                "team": null,
                "time": "+5.318",
                "laps": 36
            },
            {
                "name": "HYP - Mikkel Jensen",
                "countryCode": null,
                "team": null,
                "time": "+5.933",
                "laps": 30
            },
            {
                "name": "GT3 - Rodrigo Sales",
                "countryCode": null,
                "team": null,
                "time": "+12.110",
                "laps": 40
            },
            {
                "name": "GT3 - Benjamin Hanley",
                "countryCode": null,
                "team": null,
                "time": "+12.719",
                "laps": 35
            },
            {
                "name": "GT3 - Nick Yelloly",
                "countryCode": null,
                "team": null,
                "time": "+12.846",
                "laps": 32
            },
            {
                "name": "GT3 - Renger Van Der Zande",
                "countryCode": null,
                "team": null,
                "time": "+12.946",
                "laps": 36
            },
            {
                "name": "GT3 - Louis Delétraz",
                "countryCode": null,
                "team": null,
                "time": "+13.080",
                "laps": 40
            },
            {
                "name": "GT3 - Job Van Uitert",
                "countryCode": null,
                "team": null,
                "time": "+14.027",
                "laps": 27
            },
            {
                "name": "GT3 - George Kurtz",
                "countryCode": null,
                "team": null,
                "time": "+14.028",
                "laps": 32
            },
            {
                "name": "GT3 - Oliver Gray",
                "countryCode": null,
                "team": null,
                "time": "+14.103",
                "laps": 39
            },
            {
                "name": "GT3 - Giorgio Roda",
                "countryCode": null,
                "team": null,
                "time": "+14.438",
                "laps": 35
            },
            {
                "name": "GT3 - Antonio Felix da Costa",
                "countryCode": null,
                "team": null,
                "time": "+14.586",
                "laps": 32
            },
            {
                "name": "GT3 - Patrick Pilet",
                "countryCode": null,
                "team": null,
                "time": "+14.843",
                "laps": 38
            },
            {
                "name": "GT3 - Reshad De Gérus",
                "countryCode": null,
                "team": null,
                "time": "+14.902",
                "laps": 33
            },
            {
                "name": "GT3 - Matthias Kaiser",
                "countryCode": null,
                "team": null,
                "time": "+15.455",
                "laps": 41
            },
            {
                "name": "GT3 - Aliaksandr Malykhin",
                "countryCode": null,
                "team": null,
                "time": "+15.579",
                "laps": 38
            },
            {
                "name": "GT3 - Naveen Rao",
                "countryCode": null,
                "team": null,
                "time": "+15.885",
                "laps": 33
            },
            {
                "name": "GT3 - Jamie Chadwick",
                "countryCode": null,
                "team": null,
                "time": "+16.324",
                "laps": 32
            },
            {
                "name": "GT3 - Jean-Baptiste Simmenauer",
                "countryCode": null,
                "team": null,
                "time": "+17.027",
                "laps": 39
            },
            {
                "name": "GT3 - Zacharie Robichon",
                "countryCode": null,
                "team": null,
                "time": "+31.180",
                "laps": 32
            },
            {
                "name": "GT3 - Richard Lietz",
                "countryCode": null,
                "team": null,
                "time": "+31.217",
                "laps": 38
            },
            {
                "name": "GT3 - Finn Gehrsitz",
                "countryCode": null,
                "team": null,
                "time": "+31.307",
                "laps": 27
            },
            {
                "name": "GT3 - Valentin Hasse Clot",
                "countryCode": null,
                "team": null,
                "time": "+31.891",
                "laps": 36
            },
            {
                "name": "GT3 - Kelvin Van der Linde",
                "countryCode": null,
                "team": null,
                "time": "+32.161",
                "laps": 38
            },
            {
                "name": "GT3 - James Cottingham",
                "countryCode": null,
                "team": null,
                "time": "+32.215",
                "laps": 25
            },
            {
                "name": "GT3 - Thomas Flohr",
                "countryCode": null,
                "team": null,
                "time": "+32.229",
                "laps": 33
            },
            {
                "name": "GT3 - Antares Au",
                "countryCode": null,
                "team": null,
                "time": "+32.278",
                "laps": 36
            },
            {
                "name": "GT3 - Sean GELAEL",
                "countryCode": null,
                "team": null,
                "time": "+32.323",
                "laps": 32
            },
            {
                "name": "GT3 - jonathan hui",
                "countryCode": null,
                "team": null,
                "time": "+32.383",
                "laps": 37
            },
            {
                "name": "GT3 - Jose Maria Lopez",
                "countryCode": null,
                "team": null,
                "time": "+32.412",
                "laps": 31
            },
            {
                "name": "GT3 - Daniel Serra",
                "countryCode": null,
                "team": null,
                "time": "+32.655",
                "laps": 37
            },
            {
                "name": "GT3 - Custodio Toledo",
                "countryCode": null,
                "team": null,
                "time": "+32.665",
                "laps": 35
            },
            {
                "name": "GT3 - Simon Mann",
                "countryCode": null,
                "team": null,
                "time": "+32.694",
                "laps": 35
            },
            {
                "name": "GT3 - Charlie Eastwood",
                "countryCode": null,
                "team": null,
                "time": "+32.778",
                "laps": 38
            },
            {
                "name": "GT3 - Yasser Shahin",
                "countryCode": null,
                "team": null,
                "time": "+32.921",
                "laps": 38
            },
            {
                "name": "GT3 - Daniel Juncadella",
                "countryCode": null,
                "team": null,
                "time": "+33.024",
                "laps": 36
            },
            {
                "name": "GT3 - Ben Tuck",
                "countryCode": null,
                "team": null,
                "time": "+33.320",
                "laps": 34
            },
            {
                "name": "GT3 - Sarah Bovy",
                "countryCode": null,
                "team": null,
                "time": "+33.654",
                "laps": 39
            },
            {
                "name": "GT3 - Maxime Martin",
                "countryCode": null,
                "team": null,
                "time": "+33.713",
                "laps": 35
            },
            {
                "name": "GT3 - Lorcan Hanafin",
                "countryCode": null,
                "team": null,
                "time": "+34.197",
                "laps": 36
            },
            {
                "name": "GT3 - Brenton Grove",
                "countryCode": null,
                "team": null,
                "time": "+34.814",
                "laps": 30
            },
            {
                "name": "GT3 - Stefano Gattuso",
                "countryCode": null,
                "team": null,
                "time": "+35.477",
                "laps": 17
            },
            {
                "name": "GT3 - Lars Kern",
                "countryCode": null,
                "team": null,
                "time": "+35.668",
                "laps": 25
            }
        ]
    },
    {
        "id": "8a7cf6513",
        "results": [
            {
                "name": "HYP - Ryo Hirakawa",
                "countryCode": null,
                "team": null,
                "time": "3:26.156",
                "laps": 28
            },
            {
                "name": "HYP - Will Stevens",
                "countryCode": null,
                "team": null,
                "time": "+0.451",
                "laps": 28
            },
            {
                "name": "HYP - Yifei Ye",
                "countryCode": null,
                "team": null,
                "time": "+0.524",
                "laps": 25
            },
            {
                "name": "HYP - Pascal Wehrlein",
                "countryCode": null,
                "team": null,
                "time": "+0.592",
                "laps": 23
            },
            {
                "name": "HYP - Miguel Molina",
                "countryCode": null,
                "team": null,
                "time": "+0.653",
                "laps": 28
            },
            {
                "name": "HYP - Raffaele Marciello",
                "countryCode": null,
                "team": null,
                "time": "+1.037",
                "laps": 27
            },
            {
                "name": "HYP - Julien Andlauer",
                "countryCode": null,
                "team": null,
                "time": "+1.048",
                "laps": 23
            },
            {
                "name": "HYP - René Rast",
                "countryCode": null,
                "team": null,
                "time": "+1.098",
                "laps": 26
            },
            {
                "name": "HYP - Earl Bamber",
                "countryCode": null,
                "team": null,
                "time": "+1.129",
                "laps": 28
            },
            {
                "name": "HYP - Alessandro Pier Guidi",
                "countryCode": null,
                "team": null,
                "time": "+1.176",
                "laps": 24
            },
            {
                "name": "HYP - Paul Di Resta",
                "countryCode": null,
                "team": null,
                "time": "+1.208",
                "laps": 28
            },
            {
                "name": "HYP - Charles Milesi",
                "countryCode": null,
                "team": null,
                "time": "+1.479",
                "laps": 26
            },
            {
                "name": "HYP - Alex Riberas",
                "countryCode": null,
                "team": null,
                "time": "+1.628",
                "laps": 27
            },
            {
                "name": "HYP - Mike Conway",
                "countryCode": null,
                "team": null,
                "time": "+1.634",
                "laps": 28
            },
            {
                "name": "HYP - Jack Aitken",
                "countryCode": null,
                "team": null,
                "time": "+1.818",
                "laps": 25
            },
            {
                "name": "HYP - Nicolás Varrone",
                "countryCode": null,
                "team": null,
                "time": "+2.190",
                "laps": 22
            },
            {
                "name": "HYP - Ross Gunn",
                "countryCode": null,
                "team": null,
                "time": "+2.244",
                "laps": 24
            },
            {
                "name": "HYP - Frédéric Makowiecki",
                "countryCode": null,
                "team": null,
                "time": "+2.295",
                "laps": 27
            },
            {
                "name": "HYP - Malthe Jakobsen",
                "countryCode": null,
                "team": null,
                "time": "+2.374",
                "laps": 24
            },
            {
                "name": "HYP - Ricky Taylor",
                "countryCode": null,
                "team": null,
                "time": "+2.753",
                "laps": 25
            },
            {
                "name": "HYP - Matt Campbell",
                "countryCode": null,
                "team": null,
                "time": "+3.386",
                "laps": 20
            },
            {
                "name": "GT3 - Dane Cameron",
                "countryCode": null,
                "team": null,
                "time": "+11.359",
                "laps": 26
            },
            {
                "name": "GT3 - Renger Van Der Zande",
                "countryCode": null,
                "team": null,
                "time": "+12.488",
                "laps": 25
            },
            {
                "name": "GT3 - Aliaksandr Malykhin",
                "countryCode": null,
                "team": null,
                "time": "+12.564",
                "laps": 24
            },
            {
                "name": "GT3 - Rodrigo Sales",
                "countryCode": null,
                "team": null,
                "time": "+12.819",
                "laps": 25
            },
            {
                "name": "GT3 - Esteban Masson",
                "countryCode": null,
                "team": null,
                "time": "+12.841",
                "laps": 27
            },
            {
                "name": "GT3 - Matthieu Vaxiviere",
                "countryCode": null,
                "team": null,
                "time": "+13.204",
                "laps": 26
            },
            {
                "name": "GT3 - Cem Bölükbaşi",
                "countryCode": null,
                "team": null,
                "time": "+13.366",
                "laps": 24
            },
            {
                "name": "GT3 - Lorenzo Fluxa",
                "countryCode": null,
                "team": null,
                "time": "+13.403",
                "laps": 26
            },
            {
                "name": "GT3 - Maceo Capietto",
                "countryCode": null,
                "team": null,
                "time": "+13.404",
                "laps": 26
            },
            {
                "name": "GT3 - Jakub Smiechowski",
                "countryCode": null,
                "team": null,
                "time": "+13.405",
                "laps": 26
            },
            {
                "name": "GT3 - Rene Binder",
                "countryCode": null,
                "team": null,
                "time": "+13.586",
                "laps": 26
            },
            {
                "name": "GT3 - Daniel Schneider",
                "countryCode": null,
                "team": null,
                "time": "+13.684",
                "laps": 25
            },
            {
                "name": "GT3 - Nicky Catsburg",
                "countryCode": null,
                "team": null,
                "time": "+13.777",
                "laps": 24
            },
            {
                "name": "GT3 - Sebastian Alvarez",
                "countryCode": null,
                "team": null,
                "time": "+13.803",
                "laps": 25
            },
            {
                "name": "GT3 - Michael Jensen",
                "countryCode": null,
                "team": null,
                "time": "+14.335",
                "laps": 25
            },
            {
                "name": "GT3 - Jamie Chadwick",
                "countryCode": null,
                "team": null,
                "time": "+14.771",
                "laps": 25
            },
            {
                "name": "GT3 - Luca Ghiotto",
                "countryCode": null,
                "team": null,
                "time": "+15.361",
                "laps": 26
            },
            {
                "name": "GT3 - Jose Maria Lopez",
                "countryCode": null,
                "team": null,
                "time": "+29.266",
                "laps": 21
            },
            {
                "name": "GT3 - Jack Hawksworth",
                "countryCode": null,
                "team": null,
                "time": "+29.293",
                "laps": 20
            },
            {
                "name": "GT3 - Ryan Hardwick",
                "countryCode": null,
                "team": null,
                "time": "+29.830",
                "laps": 26
            },
            {
                "name": "GT3 - Casper Stevenson",
                "countryCode": null,
                "team": null,
                "time": "+30.438",
                "laps": 24
            },
            {
                "name": "GT3 - Lin Hodenius",
                "countryCode": null,
                "team": null,
                "time": "+30.757",
                "laps": 21
            },
            {
                "name": "GT3 - Mattia Drudi",
                "countryCode": null,
                "team": null,
                "time": "+30.799",
                "laps": 24
            },
            {
                "name": "GT3 - Simon Mann",
                "countryCode": null,
                "team": null,
                "time": "+30.857",
                "laps": 25
            },
            {
                "name": "GT3 - Klaus Bachler",
                "countryCode": null,
                "team": null,
                "time": "+30.980",
                "laps": 24
            },
            {
                "name": "GT3 - Francesco Castellacci",
                "countryCode": null,
                "team": null,
                "time": "+31.130",
                "laps": 25
            },
            {
                "name": "GT3 - Edward Cheever",
                "countryCode": null,
                "team": null,
                "time": "+31.214",
                "laps": 25
            },
            {
                "name": "GT3 - Kelvin Van der Linde",
                "countryCode": null,
                "team": null,
                "time": "+31.249",
                "laps": 21
            },
            {
                "name": "GT3 - Derek Deboer",
                "countryCode": null,
                "team": null,
                "time": "+31.266",
                "laps": 23
            },
            {
                "name": "GT3 - Grégoire Saucy",
                "countryCode": null,
                "team": null,
                "time": "+31.416",
                "laps": 25
            },
            {
                "name": "GT3 - Benjamin Barker",
                "countryCode": null,
                "team": null,
                "time": "+31.880",
                "laps": 21
            },
            {
                "name": "GT3 - Lilou Wadoux",
                "countryCode": null,
                "team": null,
                "time": "+32.130",
                "laps": 15
            },
            {
                "name": "GT3 - Marino Sato",
                "countryCode": null,
                "team": null,
                "time": "+32.716",
                "laps": 17
            },
            {
                "name": "GT3 - Lorcan Hanafin",
                "countryCode": null,
                "team": null,
                "time": "+32.740",
                "laps": 25
            },
            {
                "name": "GT3 - Orey Fidani",
                "countryCode": null,
                "team": null,
                "time": "+32.810",
                "laps": 22
            },
            {
                "name": "GT3 - Rui Andrade",
                "countryCode": null,
                "team": null,
                "time": "+32.853",
                "laps": 25
            },
            {
                "name": "GT3 - Stefano Gattuso",
                "countryCode": null,
                "team": null,
                "time": "+32.909",
                "laps": 22
            },
            {
                "name": "GT3 - Augusto Farfus",
                "countryCode": null,
                "team": null,
                "time": "+32.985",
                "laps": 22
            },
            {
                "name": "GT3 - Célia Martin",
                "countryCode": null,
                "team": null,
                "time": "+33.059",
                "laps": 25
            },
            {
                "name": "GT3 - Ben Keating",
                "countryCode": null,
                "team": null,
                "laps": 0
            },
            {
                "name": "GT3 - Stephen Grove",
                "countryCode": null,
                "team": null,
                "laps": 0
            }
        ]
    },
    {
        "id": "6869efe03",
        "results": [
            {
                "name": "GT3 - Louis Delétraz",
                "countryCode": null,
                "team": null,
                "time": "3:35.472",
                "laps": 7
            },
            {
                "name": "GT3 - Benjamin Hanley",
                "countryCode": null,
                "team": null,
                "time": "+0.185",
                "laps": 7
            },
            {
                "name": "GT3 - Alexander Quinn",
                "countryCode": null,
                "team": null,
                "time": "+0.482",
                "laps": 8
            },
            {
                "name": "GT3 - Mathias Beche",
                "countryCode": null,
                "team": null,
                "time": "+0.691",
                "laps": 8
            },
            {
                "name": "GT3 - Pietro Fittipaldi",
                "countryCode": null,
                "team": null,
                "time": "+1.064",
                "laps": 8
            },
            {
                "name": "GT3 - Esteban Masson",
                "countryCode": null,
                "team": null,
                "time": "+1.116",
                "laps": 8
            },
            {
                "name": "GT3 - Théo Pourchaire",
                "countryCode": null,
                "team": null,
                "time": "+1.140",
                "laps": 8
            },
            {
                "name": "GT3 - Nick Yelloly",
                "countryCode": null,
                "team": null,
                "time": "+1.486",
                "laps": 7
            },
            {
                "name": "GT3 - Job Van Uitert",
                "countryCode": null,
                "team": null,
                "time": "+1.532",
                "laps": 8
            },
            {
                "name": "GT3 - Patrick Pilet",
                "countryCode": null,
                "team": null,
                "time": "+1.647",
                "laps": 8
            },
            {
                "name": "GT3 - Matthieu Vaxiviere",
                "countryCode": null,
                "team": null,
                "time": "+1.922",
                "laps": 8
            },
            {
                "name": "GT3 - Tom Blomqvist",
                "countryCode": null,
                "team": null,
                "time": "+2.180",
                "laps": 7
            },
            {
                "name": "GT3 - Bent Viscaal",
                "countryCode": null,
                "team": null,
                "time": "+2.295",
                "laps": 7
            },
            {
                "name": "GT3 - André Lotterer",
                "countryCode": null,
                "team": null,
                "time": "+2.468",
                "laps": 8
            },
            {
                "name": "GT3 - Reshad De Gérus",
                "countryCode": null,
                "team": null,
                "time": "+3.076",
                "laps": 7
            },
            {
                "name": "GT3 - Luca Ghiotto",
                "countryCode": null,
                "team": null,
                "time": "+3.856",
                "laps": 6
            },
            {
                "name": "GT3 - Colin Braun",
                "countryCode": null,
                "team": null,
                "time": "+4.799",
                "laps": 7
            },
            {
                "name": "GT3 - Ahmad Al Harthy",
                "countryCode": null,
                "team": null,
                "time": "+21.403",
                "laps": 7
            },
            {
                "name": "GT3 - Ian James",
                "countryCode": null,
                "team": null,
                "time": "+21.611",
                "laps": 7
            },
            {
                "name": "GT3 - Ryan Hardwick",
                "countryCode": null,
                "team": null,
                "time": "+21.783",
                "laps": 7
            },
            {
                "name": "GT3 - Arnold Robin",
                "countryCode": null,
                "team": null,
                "time": "+21.849",
                "laps": 7
            },
            {
                "name": "GT3 - Tom Van Rompuy",
                "countryCode": null,
                "team": null,
                "time": "+22.218",
                "laps": 7
            },
            {
                "name": "GT3 - Stefano Gattuso",
                "countryCode": null,
                "team": null,
                "time": "+22.355",
                "laps": 7
            },
            {
                "name": "GT3 - jonathan hui",
                "countryCode": null,
                "team": null,
                "time": "+22.488",
                "laps": 7
            },
            {
                "name": "GT3 - James Cottingham",
                "countryCode": null,
                "team": null,
                "time": "+22.634",
                "laps": 7
            },
            {
                "name": "GT3 - François Hériau",
                "countryCode": null,
                "team": null,
                "time": "+22.644",
                "laps": 7
            },
            {
                "name": "GT3 - Thomas Flohr",
                "countryCode": null,
                "team": null,
                "time": "+23.160",
                "laps": 7
            },
            {
                "name": "GT3 - Martin Berry",
                "countryCode": null,
                "team": null,
                "time": "+23.260",
                "laps": 6
            },
            {
                "name": "GT3 - Darren Leung",
                "countryCode": null,
                "team": null,
                "time": "+23.505",
                "laps": 7
            },
            {
                "name": "GT3 - Bernardo Sousa",
                "countryCode": null,
                "team": null,
                "time": "+23.532",
                "laps": 7
            },
            {
                "name": "GT3 - Petru Umbrărescu",
                "countryCode": null,
                "team": null,
                "time": "+23.565",
                "laps": 6
            },
            {
                "name": "GT3 - Takeshi Kimura",
                "countryCode": null,
                "team": null,
                "time": "+23.620",
                "laps": 7
            },
            {
                "name": "GT3 - Yasser Shahin",
                "countryCode": null,
                "team": null,
                "time": "+23.816",
                "laps": 7
            },
            {
                "name": "GT3 - Ben Keating",
                "countryCode": null,
                "team": null,
                "time": "+23.907",
                "laps": 7
            },
            {
                "name": "GT3 - Derek Deboer",
                "countryCode": null,
                "team": null,
                "time": "+24.000",
                "laps": 7
            },
            {
                "name": "GT3 - Célia Martin",
                "countryCode": null,
                "team": null,
                "time": "+24.554",
                "laps": 7
            },
            {
                "name": "GT3 - Antares Au",
                "countryCode": null,
                "team": null,
                "time": "+24.978",
                "laps": 7
            },
            {
                "name": "GT3 - Orey Fidani",
                "countryCode": null,
                "team": null,
                "time": "+25.627",
                "laps": 7
            },
            {
                "name": "GT3 - Andrew Gilbert",
                "countryCode": null,
                "team": null,
                "time": "+0.000",
                "laps": 3
            },
            {
                "name": "GT3 - Stephen Grove",
                "countryCode": null,
                "team": null,
                "laps": 0
            },
            {
                "name": "GT3 - Custodio Toledo",
                "countryCode": null,
                "team": null,
                "time": "+0.000",
                "laps": 6
            }
        ]
    },
    {
        "id": "df27d2e23",
        "results": [
            {
                "name": "GT3 - Louis Delétraz",
                "countryCode": null,
                "team": null,
                "time": "3:35.472",
                "laps": 7
            },
            {
                "name": "GT3 - Benjamin Hanley",
                "countryCode": null,
                "team": null,
                "time": "+0.185",
                "laps": 7
            },
            {
                "name": "GT3 - Alexander Quinn",
                "countryCode": null,
                "team": null,
                "time": "+0.482",
                "laps": 8
            },
            {
                "name": "GT3 - Mathias Beche",
                "countryCode": null,
                "team": null,
                "time": "+0.691",
                "laps": 8
            },
            {
                "name": "GT3 - Pietro Fittipaldi",
                "countryCode": null,
                "team": null,
                "time": "+1.064",
                "laps": 8
            },
            {
                "name": "GT3 - Esteban Masson",
                "countryCode": null,
                "team": null,
                "time": "+1.116",
                "laps": 8
            },
            {
                "name": "GT3 - Théo Pourchaire",
                "countryCode": null,
                "team": null,
                "time": "+1.140",
                "laps": 8
            },
            {
                "name": "GT3 - Nick Yelloly",
                "countryCode": null,
                "team": null,
                "time": "+1.486",
                "laps": 7
            },
            {
                "name": "GT3 - Job Van Uitert",
                "countryCode": null,
                "team": null,
                "time": "+1.532",
                "laps": 8
            },
            {
                "name": "GT3 - Patrick Pilet",
                "countryCode": null,
                "team": null,
                "time": "+1.647",
                "laps": 8
            },
            {
                "name": "GT3 - Matthieu Vaxiviere",
                "countryCode": null,
                "team": null,
                "time": "+1.922",
                "laps": 8
            },
            {
                "name": "GT3 - Tom Blomqvist",
                "countryCode": null,
                "team": null,
                "time": "+2.180",
                "laps": 7
            },
            {
                "name": "GT3 - Bent Viscaal",
                "countryCode": null,
                "team": null,
                "time": "+2.295",
                "laps": 7
            },
            {
                "name": "GT3 - André Lotterer",
                "countryCode": null,
                "team": null,
                "time": "+2.468",
                "laps": 8
            },
            {
                "name": "GT3 - Reshad De Gérus",
                "countryCode": null,
                "team": null,
                "time": "+3.076",
                "laps": 7
            },
            {
                "name": "GT3 - Luca Ghiotto",
                "countryCode": null,
                "team": null,
                "time": "+3.856",
                "laps": 6
            },
            {
                "name": "GT3 - Colin Braun",
                "countryCode": null,
                "team": null,
                "time": "+4.799",
                "laps": 7
            },
            {
                "name": "GT3 - Ahmad Al Harthy",
                "countryCode": null,
                "team": null,
                "time": "+21.403",
                "laps": 7
            },
            {
                "name": "GT3 - Ian James",
                "countryCode": null,
                "team": null,
                "time": "+21.611",
                "laps": 7
            },
            {
                "name": "GT3 - Ryan Hardwick",
                "countryCode": null,
                "team": null,
                "time": "+21.783",
                "laps": 7
            },
            {
                "name": "GT3 - Arnold Robin",
                "countryCode": null,
                "team": null,
                "time": "+21.849",
                "laps": 7
            },
            {
                "name": "GT3 - Tom Van Rompuy",
                "countryCode": null,
                "team": null,
                "time": "+22.218",
                "laps": 7
            },
            {
                "name": "GT3 - Stefano Gattuso",
                "countryCode": null,
                "team": null,
                "time": "+22.355",
                "laps": 7
            },
            {
                "name": "GT3 - jonathan hui",
                "countryCode": null,
                "team": null,
                "time": "+22.488",
                "laps": 7
            },
            {
                "name": "GT3 - James Cottingham",
                "countryCode": null,
                "team": null,
                "time": "+22.634",
                "laps": 7
            },
            {
                "name": "GT3 - François Hériau",
                "countryCode": null,
                "team": null,
                "time": "+22.644",
                "laps": 7
            },
            {
                "name": "GT3 - Thomas Flohr",
                "countryCode": null,
                "team": null,
                "time": "+23.160",
                "laps": 7
            },
            {
                "name": "GT3 - Martin Berry",
                "countryCode": null,
                "team": null,
                "time": "+23.260",
                "laps": 6
            },
            {
                "name": "GT3 - Darren Leung",
                "countryCode": null,
                "team": null,
                "time": "+23.505",
                "laps": 7
            },
            {
                "name": "GT3 - Bernardo Sousa",
                "countryCode": null,
                "team": null,
                "time": "+23.532",
                "laps": 7
            },
            {
                "name": "GT3 - Petru Umbrărescu",
                "countryCode": null,
                "team": null,
                "time": "+23.565",
                "laps": 6
            },
            {
                "name": "GT3 - Takeshi Kimura",
                "countryCode": null,
                "team": null,
                "time": "+23.620",
                "laps": 7
            },
            {
                "name": "GT3 - Yasser Shahin",
                "countryCode": null,
                "team": null,
                "time": "+23.816",
                "laps": 7
            },
            {
                "name": "GT3 - Ben Keating",
                "countryCode": null,
                "team": null,
                "time": "+23.907",
                "laps": 7
            },
            {
                "name": "GT3 - Derek Deboer",
                "countryCode": null,
                "team": null,
                "time": "+24.000",
                "laps": 7
            },
            {
                "name": "GT3 - Célia Martin",
                "countryCode": null,
                "team": null,
                "time": "+24.554",
                "laps": 7
            },
            {
                "name": "GT3 - Antares Au",
                "countryCode": null,
                "team": null,
                "time": "+24.978",
                "laps": 7
            },
            {
                "name": "GT3 - Orey Fidani",
                "countryCode": null,
                "team": null,
                "time": "+25.627",
                "laps": 7
            },
            {
                "name": "GT3 - Andrew Gilbert",
                "countryCode": null,
                "team": null,
                "time": "+0.000",
                "laps": 3
            },
            {
                "name": "GT3 - Stephen Grove",
                "countryCode": null,
                "team": null,
                "laps": 0
            },
            {
                "name": "GT3 - Custodio Toledo",
                "countryCode": null,
                "team": null,
                "time": "+0.000",
                "laps": 6
            }
        ]
    },
    {
        "id": "479f499df",
        "results": [
            {
                "name": "HYP - Jenson Button",
                "countryCode": null,
                "team": null,
                "time": "3:25.148",
                "laps": 31
            },
            {
                "name": "HYP - Nicklas Nielsen",
                "countryCode": null,
                "team": null,
                "time": "+0.154",
                "laps": 41
            },
            {
                "name": "HYP - Matt Campbell",
                "countryCode": null,
                "team": null,
                "time": "+0.420",
                "laps": 41
            },
            {
                "name": "HYP - Ryo Hirakawa",
                "countryCode": null,
                "team": null,
                "time": "+0.554",
                "laps": 44
            },
            {
                "name": "HYP - Michael Christensen",
                "countryCode": null,
                "team": null,
                "time": "+0.596",
                "laps": 26
            },
            {
                "name": "HYP - Will Stevens",
                "countryCode": null,
                "team": null,
                "time": "+0.784",
                "laps": 40
            },
            {
                "name": "HYP - Felipe Nasr",
                "countryCode": null,
                "team": null,
                "time": "+0.814",
                "laps": 29
            },
            {
                "name": "HYP - Dries Vanthoor",
                "countryCode": null,
                "team": null,
                "time": "+0.874",
                "laps": 39
            },
            {
                "name": "HYP - Paul-Loup Chatin",
                "countryCode": null,
                "team": null,
                "time": "+0.972",
                "laps": 40
            },
            {
                "name": "HYP - Neel Jani",
                "countryCode": null,
                "team": null,
                "time": "+1.076",
                "laps": 37
            },
            {
                "name": "HYP - Kamui Kobayashi",
                "countryCode": null,
                "team": null,
                "time": "+1.123",
                "laps": 44
            },
            {
                "name": "HYP - René Rast",
                "countryCode": null,
                "team": null,
                "time": "+1.276",
                "laps": 38
            },
            {
                "name": "HYP - Ricky Taylor",
                "countryCode": null,
                "team": null,
                "time": "+1.401",
                "laps": 36
            },
            {
                "name": "HYP - Mick Schumacher",
                "countryCode": null,
                "team": null,
                "time": "+1.624",
                "laps": 39
            },
            {
                "name": "HYP - James Calado",
                "countryCode": null,
                "team": null,
                "time": "+1.716",
                "laps": 40
            },
            {
                "name": "HYP - Jack Aitken",
                "countryCode": null,
                "team": null,
                "time": "+1.750",
                "laps": 33
            },
            {
                "name": "HYP - Tom Gamble",
                "countryCode": null,
                "team": null,
                "time": "+1.920",
                "laps": 42
            },
            {
                "name": "HYP - Marco Sørensen",
                "countryCode": null,
                "team": null,
                "time": "+2.243",
                "laps": 44
            },
            {
                "name": "HYP - Philip Hanson",
                "countryCode": null,
                "team": null,
                "time": "+2.287",
                "laps": 41
            },
            {
                "name": "HYP - Mikkel Jensen",
                "countryCode": null,
                "team": null,
                "time": "+3.613",
                "laps": 38
            },
            {
                "name": "HYP - Stoffel Vandoorne",
                "countryCode": null,
                "team": null,
                "time": "+3.979",
                "laps": 36
            },
            {
                "name": "GT3 - Ryan Cullen",
                "countryCode": null,
                "team": null,
                "time": "+11.740",
                "laps": 33
            },
            {
                "name": "GT3 - Tom Dillmann",
                "countryCode": null,
                "team": null,
                "time": "+11.977",
                "laps": 38
            },
            {
                "name": "GT3 - George Kurtz",
                "countryCode": null,
                "team": null,
                "time": "+12.194",
                "laps": 38
            },
            {
                "name": "GT3 - Franck Perera",
                "countryCode": null,
                "team": null,
                "time": "+12.229",
                "laps": 38
            },
            {
                "name": "GT3 - Rodrigo Sales",
                "countryCode": null,
                "team": null,
                "time": "+12.584",
                "laps": 38
            },
            {
                "name": "GT3 - Mathys Jaubert",
                "countryCode": null,
                "team": null,
                "time": "+12.866",
                "laps": 40
            },
            {
                "name": "GT3 - Sebastian Alvarez",
                "countryCode": null,
                "team": null,
                "time": "+13.017",
                "laps": 30
            },
            {
                "name": "GT3 - Rene Binder",
                "countryCode": null,
                "team": null,
                "time": "+13.096",
                "laps": 36
            },
            {
                "name": "GT3 - Oliver Jarvis",
                "countryCode": null,
                "team": null,
                "time": "+13.219",
                "laps": 28
            },
            {
                "name": "GT3 - Matthias Kaiser",
                "countryCode": null,
                "team": null,
                "time": "+13.377",
                "laps": 42
            },
            {
                "name": "GT3 - PJ Hyett",
                "countryCode": null,
                "team": null,
                "time": "+13.431",
                "laps": 35
            },
            {
                "name": "GT3 - Matthieu Vaxiviere",
                "countryCode": null,
                "team": null,
                "time": "+13.705",
                "laps": 34
            },
            {
                "name": "GT3 - Maceo Capietto",
                "countryCode": null,
                "team": null,
                "time": "+14.013",
                "laps": 36
            },
            {
                "name": "GT3 - Jean-Baptiste Simmenauer",
                "countryCode": null,
                "team": null,
                "time": "+14.559",
                "laps": 43
            },
            {
                "name": "GT3 - Tristan Vautier",
                "countryCode": null,
                "team": null,
                "time": "+14.709",
                "laps": 36
            },
            {
                "name": "GT3 - David Heinemeier Hansson",
                "countryCode": null,
                "team": null,
                "time": "+14.799",
                "laps": 27
            },
            {
                "name": "GT3 - Colin Braun",
                "countryCode": null,
                "team": null,
                "time": "+15.748",
                "laps": 35
            },
            {
                "name": "GT3 - Arnold Robin",
                "countryCode": null,
                "team": null,
                "time": "+32.100",
                "laps": 32
            },
            {
                "name": "GT3 - Francesco Castellacci",
                "countryCode": null,
                "team": null,
                "time": "+32.147",
                "laps": 33
            },
            {
                "name": "GT3 - Valentin Hasse Clot",
                "countryCode": null,
                "team": null,
                "time": "+32.196",
                "laps": 35
            },
            {
                "name": "GT3 - Edward Cheever",
                "countryCode": null,
                "team": null,
                "time": "+32.313",
                "laps": 33
            },
            {
                "name": "GT3 - Simon Mann",
                "countryCode": null,
                "team": null,
                "time": "+32.409",
                "laps": 38
            },
            {
                "name": "GT3 - Ryan Hardwick",
                "countryCode": null,
                "team": null,
                "time": "+32.415",
                "laps": 37
            },
            {
                "name": "GT3 - Zacharie Robichon",
                "countryCode": null,
                "team": null,
                "time": "+32.475",
                "laps": 34
            },
            {
                "name": "GT3 - Daniel Serra",
                "countryCode": null,
                "team": null,
                "time": "+32.646",
                "laps": 38
            },
            {
                "name": "GT3 - Lin Hodenius",
                "countryCode": null,
                "team": null,
                "time": "+32.665",
                "laps": 33
            },
            {
                "name": "GT3 - Jose Maria Lopez",
                "countryCode": null,
                "team": null,
                "time": "+32.736",
                "laps": 32
            },
            {
                "name": "GT3 - Ahmad Al Harthy",
                "countryCode": null,
                "team": null,
                "time": "+32.761",
                "laps": 35
            },
            {
                "name": "GT3 - Riccardo Agostini",
                "countryCode": null,
                "team": null,
                "time": "+32.865",
                "laps": 35
            },
            {
                "name": "GT3 - Jonny Edgar",
                "countryCode": null,
                "team": null,
                "time": "+33.010",
                "laps": 38
            },
            {
                "name": "GT3 - Bernardo Sousa",
                "countryCode": null,
                "team": null,
                "time": "+33.098",
                "laps": 32
            },
            {
                "name": "GT3 - Sébastien Baud",
                "countryCode": null,
                "team": null,
                "time": "+33.250",
                "laps": 33
            },
            {
                "name": "GT3 - Dennis Olsen",
                "countryCode": null,
                "team": null,
                "time": "+33.258",
                "laps": 33
            },
            {
                "name": "GT3 - Antares Au",
                "countryCode": null,
                "team": null,
                "time": "+33.277",
                "laps": 36
            },
            {
                "name": "GT3 - Andrew Gilbert",
                "countryCode": null,
                "team": null,
                "time": "+33.311",
                "laps": 34
            },
            {
                "name": "GT3 - Rui Andrade",
                "countryCode": null,
                "team": null,
                "time": "+33.542",
                "laps": 39
            },
            {
                "name": "GT3 - Sean GELAEL",
                "countryCode": null,
                "team": null,
                "time": "+33.769",
                "laps": 31
            },
            {
                "name": "GT3 - Timur Boguslavskiy",
                "countryCode": null,
                "team": null,
                "time": "+34.364",
                "laps": 34
            },
            {
                "name": "GT3 - Sarah BOVY",
                "countryCode": null,
                "team": null,
                "time": "+34.441",
                "laps": 35
            },
            {
                "name": "GT3 - Matthew Bell",
                "countryCode": null,
                "team": null,
                "time": "+34.679",
                "laps": 35
            },
            {
                "name": "GT3 - Stephen Grove",
                "countryCode": null,
                "team": null,
                "time": "+36.093",
                "laps": 14
            }
        ]
    }
]