[
    {
        "id": "a6103d4b3",
        "results": [
            {
                "name": "Andrea Kimi Antonelli",
                "countryCode": "IT",
                "team": "Mercedes AMG Motorsport",
                "time": "1:13.402",
                "laps": 33
            },
            {
                "name": "George Russell",
                "countryCode": "GB",
                "team": "Mercedes AMG Motorsport",
                "time": "+0.142",
                "laps": 35
            },
            {
                "name": "Lewis Hamilton",
                "countryCode": "GB",
                "team": "Ferrari",
                "time": "+0.774",
                "laps": 36
            },
            {
                "name": "Charles Leclerc",
                "countryCode": "MC",
                "team": "Ferrari",
                "time": "+0.953",
                "laps": 36
            },
            {
                "name": "Max Verstappen",
                "countryCode": "NL",
                "team": "Red Bull Racing",
                "time": "+0.964",
                "laps": 31
            },
            {
                "name": "Lando Norris",
                "countryCode": "GB",
                "team": "McLaren",
                "time": "+1.397",
                "laps": 32
            },
            {
                "name": "Oscar Piastri",
                "countryCode": "AU",
                "team": "McLaren",
                "time": "+1.561",
                "laps": 32
            },
            {
                "name": "Arvid Lindblad",
                "countryCode": "GB",
                "team": "Racing Bulls",
                "time": "+2.050",
                "laps": 33
            },
            {
                "name": "Nico Hulkenberg",
                "countryCode": "DE",
                "team": "Audi F1 Team",
                "time": "+2.296",
                "laps": 28
            },
            {
                "name": "Fernando Alonso",
                "countryCode": "ES",
                "team": "Aston Martin F1 Team",
                "time": "+2.461",
                "laps": 31
            },
            {
                "name": "Gabriel Bortoleto",
                "countryCode": "BR",
                "team": "Audi F1 Team",
                "time": "+2.812",
                "laps": 33
            },
            {
                "name": "Isack Hadjar",
                "countryCode": "FR",
                "team": "Red Bull Racing",
                "time": "+2.851",
                "laps": 29
            },
            {
                "name": "Esteban Ocon",
                "countryCode": "FR",
                "team": "Haas F1 Team",
                "time": "+3.095",
                "laps": 32
            },
            {
                "name": "Alexander Albon",
                "countryCode": "TH",
                "team": "Williams",
                "time": "+3.240",
                "laps": 15
            },
            {
                "name": "Carlos Sainz Jr.",
                "countryCode": "ES",
                "team": "Williams",
                "time": "+3.258",
                "laps": 36
            },
            {
                "name": "Pierre Gasly",
                "countryCode": "FR",
                "team": "Alpine F1 Team",
                "time": "+3.407",
                "laps": 29
            },
            {
                "name": "Lance Stroll",
                "countryCode": "CA",
                "team": "Aston Martin F1 Team",
                "time": "+3.576",
                "laps": 30
            },
            {
                "name": "Liam Lawson",
                "countryCode": "NZ",
                "team": "Racing Bulls",
                "time": "+4.029",
                "laps": 5
            },
            {
                "name": "Oliver Bearman",
                "countryCode": "GB",
                "team": "Haas F1 Team",
                "time": "+4.368",
                "laps": 26
            },
            {
                "name": "Valtteri Bottas",
                "countryCode": "FI",
                "team": "Cadillac",
                "time": "+4.466",
                "laps": 28
            },
            {
                "name": "Sergio Perez",
                "countryCode": "MX",
                "team": "Cadillac",
                "time": "+4.524",
                "laps": 28
            },
            {
                "name": "Franco Colapinto",
                "countryCode": "AR",
                "team": "Alpine F1 Team",
                "laps": 1
            }
        ]
    },
    {
        "id": "746338f1c",
        "results": [
            {
                "name": "George Russell",
                "countryCode": "GB",
                "team": "Mercedes AMG Motorsport",
                "time": "1:12.965",
                "laps": 19
            },
            {
                "name": "Andrea Kimi Antonelli",
                "countryCode": "IT",
                "team": "Mercedes AMG Motorsport",
                "time": "+0.068",
                "laps": 16
            },
            {
                "name": "Lando Norris",
                "countryCode": "GB",
                "team": "McLaren",
                "time": "+0.315",
                "laps": 15
            },
            {
                "name": "Oscar Piastri",
                "countryCode": "AU",
                "team": "McLaren",
                "time": "+0.334",
                "laps": 15
            },
            {
                "name": "Lewis Hamilton",
                "countryCode": "GB",
                "team": "Ferrari",
                "time": "+0.361",
                "laps": 23
            },
            {
                "name": "Charles Leclerc",
                "countryCode": "MC",
                "team": "Ferrari",
                "time": "+0.445",
                "laps": 19
            },
            {
                "name": "Max Verstappen",
                "countryCode": "NL",
                "team": "Red Bull Racing",
                "time": "+0.539",
                "laps": 15
            },
            {
                "name": "Isack Hadjar",
                "countryCode": "FR",
                "team": "Red Bull Racing",
                "time": "+0.640",
                "laps": 17
            },
            {
                "name": "Arvid Lindblad",
                "countryCode": "GB",
                "team": "Racing Bulls",
                "time": "+0.772",
                "laps": 19
            },
            {
                "name": "Carlos Sainz Jr.",
                "countryCode": "ES",
                "team": "Williams",
                "time": "+1.571",
                "laps": 24
            },
            {
                "name": "Nico Hulkenberg",
                "countryCode": "DE",
                "team": "Audi F1 Team",
                "time": "+1.569",
                "laps": 14
            },
            {
                "name": "Gabriel Bortoleto",
                "countryCode": "BR",
                "team": "Audi F1 Team",
                "time": "+1.601",
                "laps": 14
            },
            {
                "name": "Franco Colapinto",
                "countryCode": "AR",
                "team": "Alpine F1 Team",
                "time": "+1.676",
                "laps": 16
            },
            {
                "name": "Esteban Ocon",
                "countryCode": "FR",
                "team": "Haas F1 Team",
                "time": "+1.902",
                "laps": 17
            },
            {
                "name": "Oliver Bearman",
                "countryCode": "GB",
                "team": "Haas F1 Team",
                "time": "+2.279",
                "laps": 17
            },
            {
                "name": "Fernando Alonso",
                "countryCode": "ES",
                "team": "Aston Martin F1 Team",
                "time": "+1.871",
                "laps": 7
            },
            {
                "name": "Sergio Perez",
                "countryCode": "MX",
                "team": "Cadillac",
                "time": "+2.113",
                "laps": 8
            },
            {
                "name": "Lance Stroll",
                "countryCode": "CA",
                "team": "Aston Martin F1 Team",
                "time": "+2.465",
                "laps": 9
            },
            {
                "name": "Pierre Gasly",
                "countryCode": "FR",
                "team": "Alpine F1 Team",
                "time": "+2.753",
                "laps": 8
            },
            {
                "name": "Valtteri Bottas",
                "countryCode": "FI",
                "team": "Cadillac",
                "time": "+2.977",
                "laps": 8
            },
            {
                "name": "Alexander Albon",
                "countryCode": "TH",
                "team": "Williams",
                "laps": 0
            },
            {
                "name": "Liam Lawson",
                "countryCode": "NZ",
                "team": "Racing Bulls",
                "laps": 0
            }
        ]
    },
    {
        "id": "d773f5732",
        "results": [
            {
                "name": "George Russell",
                "countryCode": "GB",
                "team": "Mercedes AMG Motorsport",
                "time": "28:50.951",
                "laps": 23
            },
            {
                "name": "Lando Norris",
                "countryCode": "GB",
                "team": "McLaren",
                "time": "+1.272",
                "laps": 23
            },
            {
                "name": "Andrea Kimi Antonelli",
                "countryCode": "IT",
                "team": "Mercedes AMG Motorsport",
                "time": "+1.843",
                "laps": 23
            },
            {
                "name": "Oscar Piastri",
                "countryCode": "AU",
                "team": "McLaren",
                "time": "+9.797",
                "laps": 23
            },
            {
                "name": "Charles Leclerc",
                "countryCode": "MC",
                "team": "Ferrari",
                "time": "+9.929",
                "laps": 23
            },
            {
                "name": "Lewis Hamilton",
                "countryCode": "GB",
                "team": "Ferrari",
                "time": "+10.545",
                "laps": 23
            },
            {
                "name": "Max Verstappen",
                "countryCode": "NL",
                "team": "Red Bull Racing",
                "time": "+15.935",
                "laps": 23
            },
            {
                "name": "Arvid Lindblad",
                "countryCode": "GB",
                "team": "Racing Bulls",
                "time": "+29.710",
                "laps": 23
            },
            {
                "name": "Franco Colapinto",
                "countryCode": "AR",
                "team": "Alpine F1 Team",
                "time": "+31.621",
                "laps": 23
            },
            {
                "name": "Carlos Sainz Jr.",
                "countryCode": "ES",
                "team": "Williams",
                "time": "+36.793",
                "laps": 23
            },
            {
                "name": "Liam Lawson",
                "countryCode": "NZ",
                "team": "Racing Bulls",
                "time": "+1:01.344",
                "laps": 23
            },
            {
                "name": "Gabriel Bortoleto",
                "countryCode": "BR",
                "team": "Audi F1 Team",
                "time": "+1:01.814",
                "laps": 23
            },
            {
                "name": "Esteban Ocon",
                "countryCode": "FR",
                "team": "Haas F1 Team",
                "time": "+1:04.209",
                "laps": 23
            },
            {
                "name": "Sergio Perez",
                "countryCode": "MX",
                "team": "Cadillac",
                "time": "+1:10.402",
                "laps": 23
            },
            {
                "name": "Nico Hulkenberg",
                "countryCode": "DE",
                "team": "Audi F1 Team",
                "time": "+1:12.158",
                "laps": 23
            },
            {
                "name": "Lance Stroll",
                "countryCode": "CA",
                "team": "Aston Martin F1 Team",
                "time": "+1 lap",
                "laps": 22
            },
            {
                "name": "Valtteri Bottas",
                "countryCode": "FI",
                "team": "Cadillac",
                "time": "+1 lap",
                "laps": 22
            },
            {
                "name": "Oliver Bearman",
                "countryCode": "GB",
                "team": "Haas F1 Team",
                "time": "+1 lap",
                "laps": 22
            },
            {
                "name": "Alexander Albon",
                "countryCode": "TH",
                "team": "Williams",
                "time": "+1 lap",
                "laps": 22
            },
            {
                "name": "Pierre Gasly",
                "countryCode": "FR",
                "team": "Alpine F1 Team",
                "time": "+1 lap",
                "laps": 22
            },
            {
                "name": "Isack Hadjar",
                "countryCode": "FR",
                "team": "Red Bull Racing",
                "time": "+3 laps",
                "laps": 20
            },
            {
                "name": "Fernando Alonso",
                "countryCode": "ES",
                "team": "Aston Martin F1 Team",
                "time": null,
                "laps": 15
            }
        ]
    },
    {
        "id": "ab7de7a24",
        "results": [
            {
                "name": "George Russell",
                "countryCode": "GB",
                "team": "Mercedes AMG Motorsport",
                "time": "1:12.578",
                "laps": 24
            },
            {
                "name": "Andrea Kimi Antonelli",
                "countryCode": "IT",
                "team": "Mercedes AMG Motorsport",
                "time": "+0.068",
                "laps": 24
            },
            {
                "name": "Lando Norris",
                "countryCode": "GB",
                "team": "McLaren",
                "time": "+0.151",
                "laps": 28
            },
            {
                "name": "Oscar Piastri",
                "countryCode": "AU",
                "team": "McLaren",
                "time": "+0.203",
                "laps": 29
            },
            {
                "name": "Lewis Hamilton",
                "countryCode": "GB",
                "team": "Ferrari",
                "time": "+0.290",
                "laps": 27
            },
            {
                "name": "Max Verstappen",
                "countryCode": "NL",
                "team": "Red Bull Racing",
                "time": "+0.329",
                "laps": 23
            },
            {
                "name": "Isack Hadjar",
                "countryCode": "FR",
                "team": "Red Bull Racing",
                "time": "+0.357",
                "laps": 22
            },
            {
                "name": "Charles Leclerc",
                "countryCode": "MC",
                "team": "Ferrari",
                "time": "+0.398",
                "laps": 29
            },
            {
                "name": "Arvid Lindblad",
                "countryCode": "GB",
                "team": "Racing Bulls",
                "time": "+0.702",
                "laps": 28
            },
            {
                "name": "Franco Colapinto",
                "countryCode": "AR",
                "team": "Alpine F1 Team",
                "time": "+1.119",
                "laps": 27
            },
            {
                "name": "Nico Hulkenberg",
                "countryCode": "DE",
                "team": "Audi F1 Team",
                "time": "+0.911",
                "laps": 21
            },
            {
                "name": "Liam Lawson",
                "countryCode": "NZ",
                "team": "Racing Bulls",
                "time": "+0.922",
                "laps": 22
            },
            {
                "name": "Gabriel Bortoleto",
                "countryCode": "BR",
                "team": "Audi F1 Team",
                "time": "+1.096",
                "laps": 22
            },
            {
                "name": "Pierre Gasly",
                "countryCode": "FR",
                "team": "Alpine F1 Team",
                "time": "+1.212",
                "laps": 20
            },
            {
                "name": "Carlos Sainz Jr.",
                "countryCode": "ES",
                "team": "Williams",
                "time": "+1.298",
                "laps": 21
            },
            {
                "name": "Oliver Bearman",
                "countryCode": "GB",
                "team": "Haas F1 Team",
                "time": "+1.441",
                "laps": 22
            },
            {
                "name": "Esteban Ocon",
                "countryCode": "FR",
                "team": "Haas F1 Team",
                "time": "+1.465",
                "laps": 12
            },
            {
                "name": "Alexander Albon",
                "countryCode": "TH",
                "team": "Williams",
                "time": "+1.471",
                "laps": 13
            },
            {
                "name": "Fernando Alonso",
                "countryCode": "ES",
                "team": "Aston Martin F1 Team",
                "time": "+1.816",
                "laps": 11
            },
            {
                "name": "Sergio Perez",
                "countryCode": "MX",
                "team": "Cadillac",
                "time": "+2.049",
                "laps": 11
            },
            {
                "name": "Lance Stroll",
                "countryCode": "CA",
                "team": "Aston Martin F1 Team",
                "time": "+2.815",
                "laps": 10
            },
            {
                "name": "Valtteri Bottas",
                "countryCode": "FI",
                "team": "Cadillac",
                "time": "+2.892",
                "laps": 10
            }
        ]
    }
]