[
    {
        "id": "40e4edf12",
        "results": [
            {
                "name": "Scott McLaughlin",
                "countryCode": "NZ",
                "time": "00:17.3134",
                "laps": 121
            },
            {
                "name": "Alex Palou",
                "countryCode": "ES",
                "time": "+0.0331",
                "laps": 99
            },
            {
                "name": "Patricio O’Ward",
                "countryCode": "MX",
                "time": "+0.1633",
                "laps": 111
            },
            {
                "name": "David Malukas",
                "countryCode": "US",
                "time": "+0.1673",
                "laps": 90
            },
            {
                "name": "Alexander Rossi",
                "countryCode": "US",
                "time": "+0.1985",
                "laps": 102
            },
            {
                "name": "Scott Dixon",
                "countryCode": "NZ",
                "time": "+0.2141",
                "laps": 74
            },
            {
                "name": "Agustin Hugo Canapino",
                "countryCode": "AR",
                "time": "+0.2144",
                "laps": 99
            },
            {
                "name": "Linus Lundqvist",
                "countryCode": "SE",
                "time": "+0.2614",
                "laps": 74
            },
            {
                "name": "Colton Herta",
                "countryCode": "US",
                "time": "+0.2769",
                "laps": 86
            },
            {
                "name": "Will Power",
                "countryCode": "AU",
                "time": "+0.2831",
                "laps": 86
            },
            {
                "name": "Graham Rahal",
                "countryCode": "US",
                "time": "+0.2949",
                "laps": 66
            },
            {
                "name": "Felix Rosenqvist",
                "countryCode": "SE",
                "time": "+0.3140",
                "laps": 89
            },
            {
                "name": "Santino Ferrucci",
                "countryCode": "US",
                "time": "+0.3436",
                "laps": 76
            },
            {
                "name": "Rinus Veekay",
                "countryCode": "NL",
                "time": "+0.3594",
                "laps": 80
            },
            {
                "name": "Josef Newgarden",
                "countryCode": "US",
                "time": "+0.4178",
                "laps": 105
            },
            {
                "name": "Nolan Siegel",
                "countryCode": "US",
                "time": "+0.4493",
                "laps": 80
            },
            {
                "name": "Pietro Fittipaldi",
                "countryCode": "BR",
                "time": "+0.4794",
                "laps": 112
            },
            {
                "name": "Kyle Kirkwood",
                "countryCode": "US",
                "time": "+0.5179",
                "laps": 58
            },
            {
                "name": "Christian Lundgaard",
                "countryCode": "DK",
                "time": "+0.5532",
                "laps": 86
            },
            {
                "name": "Romain Grosjean",
                "countryCode": "FR",
                "time": "+0.5955",
                "laps": 82
            },
            {
                "name": "Marcus Ericsson",
                "countryCode": "SE",
                "time": "+0.5970",
                "laps": 3
            },
            {
                "name": "Jack Harvey",
                "countryCode": "GB",
                "time": "+0.6002",
                "laps": 56
            },
            {
                "name": "Marcus Armstrong",
                "countryCode": "NZ",
                "time": "+0.6127",
                "laps": 77
            },
            {
                "name": "Katherine Legge",
                "countryCode": "GB",
                "time": "+0.7142",
                "laps": 63
            },
            {
                "name": "Sting Ray Robb",
                "countryCode": "US",
                "time": "+0.7907",
                "laps": 104
            },
            {
                "name": "Kyffin Simpson",
                "countryCode": "KY",
                "time": "+1.0205",
                "laps": 101
            },
            {
                "name": "Ed Carpenter",
                "countryCode": "US",
                "time": "+1.1689",
                "laps": 76
            }
        ]
    },
    {
        "id": "70de3f848",
        "results": [
            {
                "name": "Colton Herta",
                "countryCode": "US",
                "time": "00:17.1506",
                "laps": 2
            },
            {
                "name": "Scott McLaughlin",
                "countryCode": "NZ",
                "time": "00:17.1624",
                "laps": 2
            },
            {
                "name": "Alex Palou",
                "countryCode": "ES",
                "time": "00:17.2253",
                "laps": 2
            },
            {
                "name": "Will Power",
                "countryCode": "AU",
                "time": "00:17.2728",
                "laps": 2
            },
            {
                "name": "Scott Dixon",
                "countryCode": "NZ",
                "time": "00:17.2839",
                "laps": 2
            },
            {
                "name": "Patricio O’Ward",
                "countryCode": "MX",
                "time": "00:17.2963",
                "laps": 2
            },
            {
                "name": "Alexander Rossi",
                "countryCode": "US",
                "time": "00:17.2996",
                "laps": 2
            },
            {
                "name": "Santino Ferrucci",
                "countryCode": "US",
                "time": "00:17.3588",
                "laps": 2
            },
            {
                "name": "Marcus Armstrong",
                "countryCode": "NZ",
                "time": "00:17.3651",
                "laps": 2
            },
            {
                "name": "Marcus Ericsson",
                "countryCode": "SE",
                "time": "00:17.3713",
                "laps": 2
            },
            {
                "name": "Felix Rosenqvist",
                "countryCode": "SE",
                "time": "00:17.3783",
                "laps": 2
            },
            {
                "name": "Graham Rahal",
                "countryCode": "US",
                "time": "00:17.4146",
                "laps": 2
            },
            {
                "name": "Linus Lundqvist",
                "countryCode": "SE",
                "time": "00:17.4289",
                "laps": 2
            },
            {
                "name": "Rinus Veekay",
                "countryCode": "NL",
                "time": "00:17.4594",
                "laps": 2
            },
            {
                "name": "David Malukas",
                "countryCode": "US",
                "time": "00:17.4770",
                "laps": 2
            },
            {
                "name": "Nolan Siegel",
                "countryCode": "US",
                "time": "00:17.5152",
                "laps": 2
            },
            {
                "name": "Agustin Hugo Canapino",
                "countryCode": "AR",
                "time": "00:17.5264",
                "laps": 2
            },
            {
                "name": "Pietro Fittipaldi",
                "countryCode": "BR",
                "time": "00:17.5272",
                "laps": 2
            },
            {
                "name": "Jack Harvey",
                "countryCode": "GB",
                "time": "00:17.5336",
                "laps": 2
            },
            {
                "name": "Kyle Kirkwood",
                "countryCode": "US",
                "time": "00:17.5386",
                "laps": 2
            },
            {
                "name": "Romain Grosjean",
                "countryCode": "FR",
                "time": "00:17.5435",
                "laps": 2
            },
            {
                "name": "Josef Newgarden",
                "countryCode": "US",
                "time": "00:17.6097",
                "laps": 2
            },
            {
                "name": "Christian Lundgaard",
                "countryCode": "DK",
                "time": "00:17.7302",
                "laps": 2
            },
            {
                "name": "Sting Ray Robb",
                "countryCode": "US",
                "time": "00:18.1288",
                "laps": 2
            },
            {
                "name": "Ed Carpenter",
                "countryCode": "US",
                "time": "00:18.1997",
                "laps": 2
            },
            {
                "name": "Katherine Legge",
                "countryCode": "GB",
                "time": "00:18.2630",
                "laps": 2
            },
            {
                "name": "Kyffin Simpson",
                "countryCode": "KY",
                "time": "00:18.3003",
                "laps": 2
            }
        ]
    },
    {
        "id": "7bfe320a0",
        "results": [
            {
                "name": "Scott McLaughlin",
                "countryCode": "NZ",
                "time": "01:44:41.1172",
                "laps": 250
            },
            {
                "name": "Patricio O’Ward",
                "countryCode": "MX",
                "time": "+0.4814",
                "laps": 250
            },
            {
                "name": "Josef Newgarden",
                "countryCode": "US",
                "time": "+1.5174",
                "laps": 250
            },
            {
                "name": "Scott Dixon",
                "countryCode": "NZ",
                "time": "+5.0041",
                "laps": 250
            },
            {
                "name": "Rinus Veekay",
                "countryCode": "NL",
                "time": "+6.5656",
                "laps": 250
            },
            {
                "name": "Santino Ferrucci",
                "countryCode": "US",
                "time": "+7.4575",
                "laps": 250
            },
            {
                "name": "Kyle Kirkwood",
                "countryCode": "US",
                "time": "+8.4200",
                "laps": 250
            },
            {
                "name": "Alexander Rossi",
                "countryCode": "US",
                "time": "+9.3425",
                "laps": 250
            },
            {
                "name": "Marcus Ericsson",
                "countryCode": "SE",
                "time": "+10.3770",
                "laps": 250
            },
            {
                "name": "Marcus Armstrong",
                "countryCode": "NZ",
                "time": "+11.4006",
                "laps": 250
            },
            {
                "name": "Colton Herta",
                "countryCode": "US",
                "time": "+11.8114",
                "laps": 250
            },
            {
                "name": "Nolan Siegel",
                "countryCode": "US",
                "time": "+12.1279",
                "laps": 250
            },
            {
                "name": "Felix Rosenqvist",
                "countryCode": "SE",
                "time": "+12.4651",
                "laps": 250
            },
            {
                "name": "Kyffin Simpson",
                "countryCode": "KY",
                "time": "+13.5048",
                "laps": 250
            },
            {
                "name": "Sting Ray Robb",
                "countryCode": "US",
                "time": "+14.0242",
                "laps": 250
            },
            {
                "name": "Graham Rahal",
                "countryCode": "US",
                "time": "+1 lap",
                "laps": 249
            },
            {
                "name": "Katherine Legge",
                "countryCode": "GB",
                "time": "+1 lap",
                "laps": 249
            },
            {
                "name": "Will Power",
                "countryCode": "AU",
                "time": "+9 laps",
                "laps": 241
            },
            {
                "name": "Pietro Fittipaldi",
                "countryCode": "BR",
                "time": "00:19.0382",
                "laps": 228
            },
            {
                "name": "Ed Carpenter",
                "countryCode": "US",
                "time": "00:18.9929",
                "laps": 228
            },
            {
                "name": "Linus Lundqvist",
                "countryCode": "SE",
                "time": "00:18.8538",
                "laps": 209
            },
            {
                "name": "Christian Lundgaard",
                "countryCode": "DK",
                "time": "00:18.5291",
                "laps": 178
            },
            {
                "name": "Alex Palou",
                "countryCode": "ES",
                "time": "00:18.7269",
                "laps": 175
            },
            {
                "name": "Romain Grosjean",
                "countryCode": "FR",
                "time": "00:19.1375",
                "laps": 48
            },
            {
                "name": "Jack Harvey",
                "countryCode": "GB",
                "time": "00:19.4388",
                "laps": 28
            },
            {
                "name": "David Malukas",
                "countryCode": "US",
                "laps": 0
            },
            {
                "name": "Agustin Hugo Canapino",
                "countryCode": "AR",
                "laps": 0
            }
        ]
    }
]